t3co_go/__init__.py
t3co_go/app/__init__.py
t3co_go/app/pages/visualize_results.py
t3co_go/app/t3co_app.py
t3co_go/cli/__init__.py
t3co_go/cli/run_t3co_go.py
t3co_go/run/run_t3co.py
t3co_go/run/wrapper.py
t3co_go/utilities/__init__.py
t3co_go/utilities/demo_files_installer.py
t3co_go-0.1.3.dist-info/LICENSE
t3co_go-0.1.3.dist-info/METADATA
t3co_go-0.1.3.dist-info/WHEEL
t3co_go-0.1.3.dist-info/entry_points.txt
t3co_go-0.1.3.dist-info/RECORD
