Metadata-Version: 2.3
Name: t3co_go
Version: 0.1.3
Summary: A web-based dashboard for NREL's Transportation Technology Total Cost of Ownership (T3CO) tool
License: BSD-3-Clause
Keywords: tco,vehicle-cost,total-cost,vehicle-simulation,total-cost-of-ownership
Author: Harish Panneer Selvam
Author-email: harish.panneerselvam@nrel.gov
Maintainer: NREL-AVCI
Maintainer-email: t3co@nrel.gov
Requires-Python: >=3.9,<3.11
Classifier: Development Status :: 4 - Beta
Classifier: Intended Audience :: Developers
Classifier: Intended Audience :: Science/Research
Classifier: Intended Audience :: Education
Classifier: Topic :: Scientific/Engineering
Classifier: License :: OSI Approved :: BSD License
Classifier: Programming Language :: Python :: 3 :: Only
Classifier: Programming Language :: Python :: 3.9
Classifier: Programming Language :: Python :: 3.10
Requires-Dist: numpy (>=1.24,<2.0)
Requires-Dist: pandas (>=2.0.3,<3.0.0)
Requires-Dist: scipy (>=1.10.1,<2.0.0)
Requires-Dist: streamlit (>=1.41,<2.0)
Requires-Dist: t3co (>=1.0.11,<2.0.0)
Project-URL: Bug Tracker, https://github.com/NREL/t3co_go/issues
Project-URL: Documentation, https://nrel.github.io/T3CO_Go/
Project-URL: Homepage, https://www.nrel.gov/transportation/t3co.html
Project-URL: Repository, https://github.com/NREL/t3co_go
